setup.py
uff/__init__.py
uff/aperture.py
uff/channel_data.py
uff/curviliear_array.py
uff/cylindrical_wave_origin.py
uff/element.py
uff/element_geometry.py
uff/event.py
uff/excitation.py
uff/impulse_response.py
uff/linear_array.py
uff/matrix_array.py
uff/origin.py
uff/perimeter.py
uff/plane_wave_origin.py
uff/position.py
uff/probe.py
uff/receive_setup.py
uff/rotation.py
uff/spherical_wave_origin.py
uff/time_zero_reference_point.py
uff/timed_event.py
uff/transform.py
uff/translation.py
uff/transmit_event.py
uff/transmit_setup.py
uff/transmit_wave.py
uff/uff.py
uff/uff_io.py
uff/utils.py
uff/version.py
uff/wave.py
uff/wave_type.py
uff_reader-0.0.2.dist-info/METADATA
uff_reader-0.0.2.dist-info/WHEEL
uff_reader-0.0.2.dist-info/licenses/LICENSE
uff_reader-0.0.2.dist-info/RECORD
