Metadata-Version: 2.1
Name: uff-reader
Version: 0.0.2
Summary: Python interface for the Ultrasound File Format (UFF)
Author-email: Walter Simson <walter.simson@tum.de>
License-Expression: MIT
License-File: LICENSE
Requires-Dist: h5py>=3.5.0
Requires-Dist: numpy>=1.20
Requires-Dist: pytest>=6.2.4
Requires-Dist: requests>=2.26.0
Requires-Dist: scipy>=1.7.0
